MANIFEST.in
README.rst
example.pyclock.conf
pyclock.py
setup.py
PyClock.egg-info/PKG-INFO
PyClock.egg-info/SOURCES.txt
PyClock.egg-info/dependency_links.txt
PyClock.egg-info/entry_points.txt
PyClock.egg-info/top_level.txt