Metadata-Version: 1.1
Name: PyClock
Version: 1.0.0
Summary: A digital clock for the terminal
Home-page: https://github.com/Regaerd/PyClock
Author: Brandon Dreager
Author-email: pyclock@subol.es
License: MIT
Keywords: terminal,clock
Platform: UNKNOWN
Classifier: Development Status :: 4 - Beta
Classifier: Environment :: Console :: Curses
Classifier: Intended Audience :: End Users/Desktop
Classifier: License :: OSI Approved :: MIT License
Classifier: Natural Language :: English
Classifier: Operating System :: MacOS :: MacOS X
Classifier: Operating System :: POSIX :: Linux
Classifier: Programming Language :: Python :: 2.7
Classifier: Programming Language :: Python :: 3
Classifier: Topic :: Utilities
Classifier: Topic :: Terminals
